FSM_sd/0110/non_ov_0110.v
`timescale 1ns/1ps

module non_ov_0110(
    input clk,
    input rst,
    input in,
    output reg out
    );

    // parameter s0 = 1b'00, s1 = 1b'01, s2 = 1b'10, s3 = 1b'11;
    parameter s0 = 0, s1 = 1, s2 = 2, s3 = 3;
    reg [1:0] state;

    always @(posedge clk) begin
        if(rst == 1'b1) begin
            state <= s0;
            out <= 1'b0;
        end
        else begin
            case(state)
                s0: begin
                    state <= in ? s0 : s1;
                    out <= 0;
                end 
                s1: begin
                    state <= in ? s2 : s1;
                    out <= 0;
                end
                s2: begin
                    state <= in ? s3 : s1;
                    out <= 0;
                end
                s3: begin
                    state <= in ? s0 : s0;
                    out <= in ? 0 : 1;
                end
                default: begin
                    state <= s0;
                    out <= 0;
                end
            endcase
        end
    end

endmodule

FSM_sd/0110/tb_non_ov.v
`timescale 1ns/1ps
`include "non_ov_0110.v"

module tb_non_ov();

reg clk, rst, in;
wire out;

non_ov_0110 dut(.clk(clk), .rst(rst), .in(in), .out(out));

initial begin
    clk = 1'b0;
    rst = 1'b1;
    #15 rst = 1'b0;
end

initial forever begin
    #5 clk = ~clk;
end

initial begin
    $monitor("%t || in = %b || out = %b || state = %d", $time, in, out, dut.state);
    $dumpfile("non_ov.vcd");
    $dumpvars(0, tb_non_ov);
end

initial begin
    in = 0;
    #15 in = 1;
    #10 in = 0;
    #10 in = 1;
    #10 in = 1;
    #10 in = 0;
    #10 in = 1;
    #10 in = 1;
    #10 in = 0;
    #10 in = 1;
    #10 in = 0;
    #10 $finish;
end

endmodule

FSM_sd/0110/non_ov.vcd
$date
	Fri Feb 07 21:18:22 2025
$end
$version
	Icarus Verilog
$end
$timescale
	1ps
$end
$scope module tb_non_ov $end
$var wire 1 ! out $end
$var reg 1 " clk $end
$var reg 1 # in $end
$var reg 1 $ rst $end
$scope module dut $end
$var wire 1 " clk $end
$var wire 1 # in $end
$var wire 1 $ rst $end
$var parameter 32 % s0 $end
$var parameter 32 & s1 $end
$var parameter 32 ' s2 $end
$var parameter 32 ( s3 $end
$var reg 1 ! out $end
$var reg 2 ) state [1:0] $end
$upscope $end
$upscope $end
$enddefinitions $end
$comment Show the parameter values. $end
$dumpall
b11 (
b10 '
b1 &
b0 %
$end
#0
$dumpvars
bx )
1$
0#
0"
x!
$end
#5000
0!
b0 )
1"
#10000
0"
#15000
1"
1#
0$
#20000
0"
#25000
b1 )
1"
0#
#30000
0"
#35000
b10 )
1"
1#
#40000
0"
#45000
b11 )
1"
#50000
0"
#55000
1!
b0 )
1"
0#
#60000
0"
#65000
0!
1"
1#
#70000
0"
#75000
1"
#80000
0"
#85000
b1 )
1"
0#
#90000
0"
#95000
b10 )
1"
1#
#100000
0"
#105000
b1 )
1"
0#
