FSM_sd/1101/1101_non_ov.v
`timescale 1ns/1ps

module non_ov_1101(
    input clk,
    input rst,
    input in,
    output reg out
    );

    // parameter s0 = 00, s1 = 01, s2 = 10, s3 = 11;
    parameter s0 = 0, s1 = 1, s2 = 2, s3 = 3;
    reg [1:0] state;

    always @(posedge clk) begin
        if(rst == 1'b1) begin
            state <= s0;
            out <= 1'b0;
        end
        else begin
            case(state)
                s0: begin
                    state <= in ? s1 : s0;
                    out <= 0;
                end 
                s1: begin
                    state <= in ? s2 : s0;
                    out <= 0;
                end
                s2: begin
                    state <= in ? s2 : s3;
                    out <= 0;
                end
                s3: begin
                    state <= in ? s0 : s0;
                    out <= in ? 1 : 0;
                end
                default: begin
                    state <= s0;
                    out <= 0;
                end
            endcase
        end
    end

endmodule

FSM_sd/1101/1101_ov.v
`timescale 1ns/1ps

module ov_1101(
    input clk,
    input rst,
    input in,
    output reg out
    );

    // parameter s0 = 00, s1 = 01, s2 = 10, s3 = 11;
    parameter s0 = 0, s1 = 1, s2 = 2, s3 = 3;
    reg [1:0] state;

    always @(posedge clk) begin
        if(rst == 1'b1) begin
            state <= s0;
            out <= 1'b0;
        end
        else begin
            case(state)
                s0: begin
                    state <= in ? s1 : s0;
                    out <= 0;
                end 
                s1: begin
                    state <= in ? s2 : s0;
                    out <= 0;
                end
                s2: begin
                    state <= in ? s2 : s3;
                    out <= 0;
                end
                s3: begin
                    state <= in ? s1 : s0;
                    out <= in ? 1 : 0;
                end
                default: begin
                    state <= s0;
                    out <= 0;
                end
            endcase
        end
    end

endmodule

FSM_sd/1101/tb_1101.v
`timescale 1ns/1ps
// `include "1101_non_ov.v"
`include "1101_ov.v"

module tb_1101();

reg clk, rst, in;
wire out;

// non_ov_1101 dut(.clk(clk), .rst(rst), .in(in), .out(out));
ov_1101 dut(clk, rst, in, out);

initial begin
    clk = 1'b0;
    rst = 1'b1;
    #15 rst = 1'b0;
end

initial forever begin
    #5 clk = ~clk;
end

initial begin
    $monitor("%t || in = %b || out = %b || state = %d", $time, in, out, dut.state);
    // $dumpfile("tb_1101_non_ov.vcd");
    $dumpfile("tb_1101_ov.vcd");
    $dumpvars(0, tb_1101);
end

initial begin
    in = 0;
    #15 in = 0;
    #10 in = 1;
    #10 in = 1;
    #10 in = 1;
    #10 in = 0;
    #10 in = 1;
    #10 in = 1;
    #10 in = 0;
    #10 in = 1;
    #10 in = 0;
    #20 $finish;
end

endmodule

FSM_sd/1101/tb_1101_ov.vcd
$date
	Fri Feb 07 19:18:26 2025
$end
$version
	Icarus Verilog
$end
$timescale
	1ps
$end
$scope module tb_1101 $end
$var wire 1 ! out $end
$var reg 1 " clk $end
$var reg 1 # in $end
$var reg 1 $ rst $end
$scope module dut $end
$var wire 1 " clk $end
$var wire 1 # in $end
$var wire 1 $ rst $end
$var parameter 32 % s0 $end
$var parameter 32 & s1 $end
$var parameter 32 ' s2 $end
$var parameter 32 ( s3 $end
$var reg 1 ! out $end
$var reg 2 ) state [1:0] $end
$upscope $end
$upscope $end
$enddefinitions $end
$comment Show the parameter values. $end
$dumpall
b11 (
b10 '
b1 &
b0 %
$end
#0
$dumpvars
bx )
1$
0#
0"
x!
$end
#15000
0$
#20000
0!
b0 )
1"
#25000
0"
1#
#30000
b1 )
1"
#35000
0"
#40000
b10 )
1"
#45000
0"
#50000
1"
#55000
0"
0#
#60000
b11 )
1"
#65000
0"
1#
#70000
1!
b1 )
1"
#75000
0"
#80000
0!
b10 )
1"
#85000
0"
0#
#90000
b11 )
1"
#95000
0"
1#
#100000
1!
b1 )
1"
#105000
0"
0#
#110000
0!
b0 )
1"
