FSM_sd/10110/mealy_ov.v
`timescale 1ns/1ps

module mealy_ov(
    input clk,
    input rst,
    input in,
    output reg out
    );

    parameter s0 = 0, s1 = 1, s10 = 2, s101 = 3, s1011 = 4;
    reg[2:0] state;
    
    always @(posedge clk) begin
        if(rst == 1'b1) begin
            state <= s0;
            out <= 1'b0;
        end
        else begin
            case(state)
                s0: begin
                    state <= in ? s1 : s0;
                    out <= 0;
                end
                s1: begin
                    state <= in ? s1 : s10;
                    out <= 0;
                end
                s10: begin
                    state <= in ? s101 : s0;
                    out <= 0;
                end
                s101: begin
                    state <= in ? s1011 : s101;
                    out <= 0;
                end
                s1011: begin
                    state <= in ? s1 : s10;
                    out <= in ? 0 : 1;
                end 
            endcase
        end
    end

endmodule

FSM_sd/10110/tb_ov.v
`timescale 1ns/1ps
`include "mealy_ov.v"

module tb_ov();

reg clk, rst, in;
wire out;

mealy_ov dut(clk, rst, in, out);

initial begin
    clk = 1'b0;
    rst = 1'b1;
    #15 rst = 1'b0;
end

always #5 clk = ~clk;

initial begin
    $monitor("%t | in = %b | out = %b | state = %d", $time, in, out, dut.state);
    $dumpfile("ov.vcd");
    $dumpvars(0, tb_ov);
end

initial begin
    in = 0;
    #15 in = 1;
    #10 in = 0;
    #10 in = 1;
    #10 in = 1;
    #10 in = 0;
    #10 in = 1;
    #10 in = 1;
    #10 in = 0;
    #15 $stop;
end

endmodule

FSM_sd/10110/ov.vcd
$date
	Mon Feb 17 02:35:54 2025
$end
$version
	Icarus Verilog
$end
$timescale
	1ps
$end
$scope module tb_ov $end
$var wire 1 ! out $end
$var reg 1 " clk $end
$var reg 1 # in $end
$var reg 1 $ rst $end
$scope module dut $end
$var wire 1 " clk $end
$var wire 1 # in $end
$var wire 1 $ rst $end
$var parameter 32 % s0 $end
$var parameter 32 & s1 $end
$var parameter 32 ' s10 $end
$var parameter 32 ( s101 $end
$var parameter 32 ) s1011 $end
$var reg 1 ! out $end
$var reg 3 * state [2:0] $end
$upscope $end
$upscope $end
$enddefinitions $end
$comment Show the parameter values. $end
$dumpall
b100 )
b11 (
b10 '
b1 &
b0 %
$end
#0
$dumpvars
bx *
1$
0#
0"
x!
$end
#5000
0!
b0 *
1"
#10000
0"
#15000
b1 *
1"
1#
0$
#20000
0"
#25000
b10 *
1"
0#
#30000
0"
#35000
b11 *
1"
1#
#40000
0"
#45000
b100 *
1"
#50000
0"
#55000
1!
b10 *
1"
0#
#60000
0"
#65000
0!
b11 *
1"
1#
#70000
0"
#75000
b100 *
1"
#80000
0"
#85000
1!
b10 *
1"
0#
#90000
0"
#95000
0!
b0 *
1"
