Code Converters/Gray to Binary/gray2bin.v
`timescale 1ns / 1ps
//////////////////////////////////////////////////////////////////////////////////
// 
// Create Date: 02/15/2025 07:54:58 PM
// Creator Name: Sk Mahamamd Anish
// Module Name: bin2bcd
// Project Name: Code Converter
// 
// Dependencies: 
// 
// Revision 0.01 - File Created
// 
//////////////////////////////////////////////////////////////////////////////////

module gray2bin (
    input [3:0] gray,
    output [3:0] binary
);
    assign binary[3] = gray[3];
    assign binary[2] = gray[3] ^ gray[2];
    assign binary[1] = gray[3] ^ gray[2] ^ gray[1];
    assign binary[0] = gray[3] ^ gray[2] ^ gray[1] ^ gray[0];
endmodule

Code Converters/Gray to Binary/gray2bin_tb.v
`timescale 1ns / 1ps
//////////////////////////////////////////////////////////////////////////////////
// 
// Create Date: 02/15/2025 07:54:58 PM
// Creator Name: Sk Mahamamd Anish
// Module Name: bin2bcd
// Project Name: Code Converter
// 
// Dependencies: 
// 
// Revision 0.01 - File Created
// 
//////////////////////////////////////////////////////////////////////////////////

module gray2bin_tb;
    reg [3:0] gray;
    wire [3:0] binary;

    gray2bin g2b (
        .gray(gray),
        .binary(binary)
    );

    initial begin
        $monitor("%t	| gray = %b, binary = %b", $time, gray, binary);
	$dumpfile("gray2bin.vcd");
	$dumpvars(0, gray2bin_tb);	

        gray = 4'b0000; #10;
        gray = 4'b0001; #10;
        gray = 4'b0011; #10;
        gray = 4'b0010; #10;
        gray = 4'b0110; #10;
        gray = 4'b0111; #10;
        gray = 4'b0101; #10;
        gray = 4'b0100; #10;
        gray = 4'b1100; #10;
        gray = 4'b1101; #10;
        gray = 4'b1111; #10;
        gray = 4'b1110; #10;
        gray = 4'b1010; #10;
        gray = 4'b1011; #10;
        gray = 4'b1001; #10;
        gray = 4'b1000; #10;

        $finish;
    end
endmodule

Code Converters/Gray to Binary/gray2bin.vcd
$date
	Mon Feb 17 21:56:22 2025
$end
$version
	Icarus Verilog
$end
$timescale
	1ps
$end
$scope module gray2bin_tb $end
$var wire 4 ! binary [3:0] $end
$var reg 4 " gray [3:0] $end
$scope module g2b $end
$var wire 4 # gray [3:0] $end
$var wire 4 $ binary [3:0] $end
$upscope $end
$upscope $end
$enddefinitions $end
$comment Show the parameter values. $end
$dumpall
$end
#0
$dumpvars
b0 $
b0 #
b0 "
b0 !
$end
#10000
b1 !
b1 $
b1 "
b1 #
#20000
b10 !
b10 $
b11 "
b11 #
#30000
b11 !
b11 $
b10 "
b10 #
#40000
b100 !
b100 $
b110 "
b110 #
#50000
b101 !
b101 $
b111 "
b111 #
#60000
b110 !
b110 $
b101 "
b101 #
#70000
b111 !
b111 $
b100 "
b100 #
#80000
b1000 !
b1000 $
b1100 "
b1100 #
#90000
b1001 !
b1001 $
b1101 "
b1101 #
#100000
b1010 !
b1010 $
b1111 "
b1111 #
#110000
b1011 !
b1011 $
b1110 "
b1110 #
#120000
b1100 !
b1100 $
b1010 "
b1010 #
#130000
b1101 !
b1101 $
b1011 "
b1011 #
#140000
b1110 !
b1110 $
b1001 "
b1001 #
#150000
b1111 !
b1111 $
b1000 "
b1000 #
