FSM_sd/1010/ov_1010.v
`timescale 1ns/1ps

module ov_1010(
    input clk,
    input rst,
    input in,
    output reg out
    );

parameter s0 = 0, s1 = 1, s10 = 2, s101 = 3, s1010 = 4;
// parameter s0 = 0, s1 = 1, s2 = 2, s3 = 3, s4 = 4;
// parameter s0 = 3b'000, s1 = 3b'001, s2 = 3b'010, s3 = 3b'011, s4 = 3b'100;
reg [2:0] ps, ns;

// reset logic
always @(posedge clk) begin
    if(rst == 1) begin
        out <= 0;
        ps <= s0;
    end
    else ps <= ns;
end

// out + state decode logic
always @(ps, in) begin
    case(ps)
        s0: begin
            out = 0;
            ns = in ? s1 : s0;
        end
        s1: begin
            out = 0;
            ns = in ? s1 : s10;
        end
        s10: begin
            out = 0;
            ns = in ? s101 : s0;
        end
        s101: begin
            out = 0;
            ns = in ? s1 : s1010;
        end
        s1010: begin
            out = 1;
            ns = in ? s101 : s0;
        end
        default: begin
            out = 0;
            ns = s0;
        end
    endcase
end

endmodule

FSM_sd/1010/tb_ov.v
`timescale 1ns/1ps
`include "ov_1010.v"

module tb_ov();

reg clk, rst, in;
wire out;

ov_1010 dut(.clk(clk), .rst(rst), .in(in), .out(out));

initial begin
    clk = 0;
    rst = 1;
    #15 rst = 0;
end

always #5 clk = ~clk;

initial begin
    $monitor("%t || in = %b || out = %b || state = %d", $time, in, out, dut.ps);
    $dumpfile("ov.vcd");
    $dumpvars(0, tb_ov);
end

initial begin
    in = 0;
    #10 in = 1;
    #10 in = 0;
    #10 in = 1;
    #10 in = 0;
    #10 in = 1;
    #10 in = 0;
    #10 in = 1;
    #10 in = 0;
    #10 in = 1;
    #10 in = 0;
    #10 in = 1;
    #10 $finish;
end

endmodule

FSM_sd/1010/ov.vcd
$date
	Fri Feb 07 21:47:24 2025
$end
$version
	Icarus Verilog
$end
$timescale
	1ps
$end
$scope module tb_ov $end
$var wire 1 ! out $end
$var reg 1 " clk $end
$var reg 1 # in $end
$var reg 1 $ rst $end
$scope module dut $end
$var wire 1 " clk $end
$var wire 1 # in $end
$var wire 1 $ rst $end
$var parameter 32 % s0 $end
$var parameter 32 & s1 $end
$var parameter 32 ' s10 $end
$var parameter 32 ( s101 $end
$var parameter 32 ) s1010 $end
$var reg 3 * ns [2:0] $end
$var reg 1 ! out $end
$var reg 3 + ps [2:0] $end
$upscope $end
$upscope $end
$enddefinitions $end
$comment Show the parameter values. $end
$dumpall
b100 )
b11 (
b10 '
b1 &
b0 %
$end
#0
$dumpvars
bx +
b0 *
1$
0#
0"
0!
$end
#5000
b0 +
1"
#10000
b1 *
0"
1#
#15000
b1 +
1"
0$
#20000
b10 *
0"
0#
#25000
b0 *
b10 +
1"
#30000
b11 *
0"
1#
#35000
b1 *
b11 +
1"
#40000
b100 *
0"
0#
#45000
b0 *
1!
b100 +
1"
#50000
b11 *
0"
1#
#55000
b1 *
0!
b11 +
1"
#60000
b100 *
0"
0#
#65000
b0 *
1!
b100 +
1"
#70000
b11 *
0"
1#
#75000
b1 *
0!
b11 +
1"
#80000
b100 *
0"
0#
#85000
b0 *
1!
b100 +
1"
#90000
b11 *
0"
1#
#95000
b1 *
0!
b11 +
1"
#100000
b100 *
0"
0#
#105000
b0 *
1!
b100 +
1"
#110000
b11 *
0"
1#
#115000
b1 *
0!
b11 +
1"
