Lab/fa_mux/fa_mx4x1.v
module mux4x1(a, b, c, d, s1, s0, y);
    input a, b, c, d, s0, s1;
    output y;
    
    assign y = s1 ? (s0 ? d : c) : (s0 ? b : a);
endmodule

module main(a, b, cin, s, cout);

    input a, b, cin;
    output s, cout;

    wire cinbar;

    assign cinbar = ~cin;

    mux4x1 m1(cin, cinbar, cinbar, cin, a, b, s);
    mux4x1 m2(1'b0, cin, cin, 1'b1, a, b, cout);

endmodule

Lab/fa_mux/fa_mx4x1_tb.v
`timescale 1ns/1ps

module fa_mx4x1_tb;
    reg a, b, cin;
    wire s, cout;

    main dut(a, b, cin, s, cout);

    initial begin
        $dumpfile("fa_mx4x1_tb.vcd");
        $dumpvars(0, fa_mx4x1_tb);
    end

    initial begin
        a = 0; b = 0; cin = 0;
        #10 
        $display("a=%b, b=%b, cin=%b, s=%b, cout=%b", a, b, cin, s, cout);
        a = 0; b = 0; cin = 1;
        #10 
        $display("a=%b, b=%b, cin=%b, s=%b, cout=%b", a, b, cin, s, cout);
        a = 0; b = 1; cin = 0;
        #10 
        $display("a=%b, b=%b, cin=%b, s=%b, cout=%b", a, b, cin, s, cout);
        a = 0; b = 1; cin = 1;
        #10 
        $display("a=%b, b=%b, cin=%b, s=%b, cout=%b", a, b, cin, s, cout);
        a = 1; b = 0; cin = 0;
        #10 
        $display("a=%b, b=%b, cin=%b, s=%b, cout=%b", a, b, cin, s, cout);
        a = 1; b = 0; cin = 1;
        #10 
        $display("a=%b, b=%b, cin=%b, s=%b, cout=%b", a, b, cin, s, cout);
        a = 1; b = 1; cin = 0;
        #10 
        $display("a=%b, b=%b, cin=%b, s=%b, cout=%b", a, b, cin, s, cout);
        a = 1; b = 1; cin = 1;
        #10 
        $display("a=%b, b=%b, cin=%b, s=%b, cout=%b", a, b, cin, s, cout);
        $finish;
    end
endmodule

Lab/fa_mux/fa_mx4x1_tb.vcd
$date
	Thu Feb 06 00:29:31 2025
$end
$version
	Icarus Verilog
$end
$timescale
	1ps
$end
$scope module fa_mx4x1_tb $end
$var wire 1 ! s $end
$var wire 1 " cout $end
$var reg 1 # a $end
$var reg 1 $ b $end
$var reg 1 % cin $end
$scope module dut $end
$var wire 1 # a $end
$var wire 1 $ b $end
$var wire 1 % cin $end
$var wire 1 & cinbar $end
$var wire 1 ! s $end
$var wire 1 " cout $end
$scope module m1 $end
$var wire 1 % a $end
$var wire 1 & b $end
$var wire 1 & c $end
$var wire 1 % d $end
$var wire 1 $ s0 $end
$var wire 1 # s1 $end
$var wire 1 ! y $end
$upscope $end
$scope module m2 $end
$var wire 1 ' a $end
$var wire 1 % b $end
$var wire 1 % c $end
$var wire 1 ( d $end
$var wire 1 $ s0 $end
$var wire 1 # s1 $end
$var wire 1 " y $end
$upscope $end
$upscope $end
$upscope $end
$enddefinitions $end
$comment Show the parameter values. $end
$dumpall
$end
#0
$dumpvars
1(
0'
1&
0%
0$
0#
0"
0!
$end
#10000
1!
0&
1%
#20000
1!
1&
0%
1$
#30000
0!
1"
0&
1%
#40000
0"
1&
1!
0%
0$
1#
#50000
0!
1"
0&
1%
#60000
1&
0%
1$
#70000
1!
0&
1%
