Code Converters/Byte to BCD/byte2bcd.v
`timescale 1ns / 1ps
//////////////////////////////////////////////////////////////////////////////////
// 
// Create Date: 02/15/2025 07:54:58 PM
// Creator Name: Sk Mahamamd Anish
// Module Name: byte2bcd
// Project Name: Code Converter
// 
// Dependencies: 
// 
// Revision 0.01 - File Created
// 
//////////////////////////////////////////////////////////////////////////////////

module byte2bcd(
	input  [7:0] byte_in,
	output [11:0] bcd_out
);

	reg [3:0] hundreds, tens, ones;
	reg [6:0] temp_reg;

	always @(*) begin
		hundreds = byte_in / 100;
		temp_reg = byte_in % 100;
		tens = temp_reg / 10;
		ones = temp_reg % 10;
	end

	assign bcd_out = {hundreds, tens, ones};

endmodule

Code Converters/Byte to BCD/byte2bcd_TB.v
`timescale 1ns / 1ps
//////////////////////////////////////////////////////////////////////////////////
// 
// Create Date: 02/15/2025 07:54:58 PM
// Creator Name: Sk Mahamamd Anish
// Module Name: byte2bcd_TB
// Project Name: Code Converter
// 
// Dependencies: 
// 
// Revision 0.01 - File Created
// 
//////////////////////////////////////////////////////////////////////////////////

module byte2bcd_TB;

	reg  [7:0] byte_in;
	wire [11:0] bcd_out;

	byte2bcd DUT(.byte_in(byte_in), .bcd_out(bcd_out));

	integer i;
	
	initial begin
		for(i = 0; i < 256; i = i + 1) begin
			byte_in = i;
			#2;
		end
	end

	initial begin
		$monitor("%t	|	byte_in = %b --> bcd_out = %b ", $time, byte_in, bcd_out);
		$dumpfile("byte2bcd_TB.vcd") ;
		$dumpvars(0, byte2bcd_TB) ;
    	end

endmodule

Code Converters/Byte to BCD/byte2bcd_TB.vcd
$date
	Mon Feb 17 21:39:33 2025
$end
$version
	Icarus Verilog
$end
$timescale
	1ps
$end
$scope module byte2bcd_TB $end
$var wire 12 ! bcd_out [11:0] $end
$var reg 8 " byte_in [7:0] $end
$var integer 32 # i [31:0] $end
$scope module DUT $end
$var wire 8 $ byte_in [7:0] $end
$var wire 12 % bcd_out [11:0] $end
$var reg 4 & hundreds [3:0] $end
$var reg 4 ' ones [3:0] $end
$var reg 7 ( temp_reg [6:0] $end
$var reg 4 ) tens [3:0] $end
$upscope $end
$upscope $end
$enddefinitions $end
$comment Show the parameter values. $end
$dumpall
$end
#0
$dumpvars
b0 )
b0 (
b0 '
b0 &
b0 %
b0 $
b0 #
b0 "
b0 !
$end
#2000
b1 !
b1 %
b1 '
b1 (
b1 "
b1 $
b1 #
#4000
b10 !
b10 %
b10 '
b10 (
b10 "
b10 $
b10 #
#6000
b11 !
b11 %
b11 '
b11 (
b11 "
b11 $
b11 #
#8000
b100 !
b100 %
b100 '
b100 (
b100 "
b100 $
b100 #
#10000
b101 !
b101 %
b101 '
b101 (
b101 "
b101 $
b101 #
#12000
b110 !
b110 %
b110 '
b110 (
b110 "
b110 $
b110 #
#14000
b111 !
b111 %
b111 '
b111 (
b111 "
b111 $
b111 #
#16000
b1000 !
b1000 %
b1000 '
b1000 (
b1000 "
b1000 $
b1000 #
#18000
b1001 !
b1001 %
b1001 '
b1001 (
b1001 "
b1001 $
b1001 #
#20000
b0 '
b10000 !
b10000 %
b1 )
b1010 (
b1010 "
b1010 $
b1010 #
#22000
b10001 !
b10001 %
b1 '
b1011 (
b1011 "
b1011 $
b1011 #
#24000
b10010 !
b10010 %
b10 '
b1100 (
b1100 "
b1100 $
b1100 #
#26000
b10011 !
b10011 %
b11 '
b1101 (
b1101 "
b1101 $
b1101 #
#28000
b10100 !
b10100 %
b100 '
b1110 (
b1110 "
b1110 $
b1110 #
#30000
b10101 !
b10101 %
b101 '
b1111 (
b1111 "
b1111 $
b1111 #
#32000
b10110 !
b10110 %
b110 '
b10000 (
b10000 "
b10000 $
b10000 #
#34000
b10111 !
b10111 %
b111 '
b10001 (
b10001 "
b10001 $
b10001 #
#36000
b11000 !
b11000 %
b1000 '
b10010 (
b10010 "
b10010 $
b10010 #
#38000
b11001 !
b11001 %
b1001 '
b10011 (
b10011 "
b10011 $
b10011 #
#40000
b0 '
b100000 !
b100000 %
b10 )
b10100 (
b10100 "
b10100 $
b10100 #
#42000
b100001 !
b100001 %
b1 '
b10101 (
b10101 "
b10101 $
b10101 #
#44000
b100010 !
b100010 %
b10 '
b10110 (
b10110 "
b10110 $
b10110 #
#46000
b100011 !
b100011 %
b11 '
b10111 (
b10111 "
b10111 $
b10111 #
#48000
b100100 !
b100100 %
b100 '
b11000 (
b11000 "
b11000 $
b11000 #
#50000
b100101 !
b100101 %
b101 '
b11001 (
b11001 "
b11001 $
b11001 #
#52000
b100110 !
b100110 %
b110 '
b11010 (
b11010 "
b11010 $
b11010 #
#54000
b100111 !
b100111 %
b111 '
b11011 (
b11011 "
b11011 $
b11011 #
#56000
b101000 !
b101000 %
b1000 '
b11100 (
b11100 "
b11100 $
b11100 #
#58000
b101001 !
b101001 %
b1001 '
b11101 (
b11101 "
b11101 $
b11101 #
#60000
b0 '
b110000 !
b110000 %
b11 )
b11110 (
b11110 "
b11110 $
b11110 #
#62000
b110001 !
b110001 %
b1 '
b11111 (
b11111 "
b11111 $
b11111 #
#64000
b110010 !
b110010 %
b10 '
b100000 (
b100000 "
b100000 $
b100000 #
#66000
b110011 !
b110011 %
b11 '
b100001 (
b100001 "
b100001 $
b100001 #
#68000
b110100 !
b110100 %
b100 '
b100010 (
b100010 "
b100010 $
b100010 #
#70000
b110101 !
b110101 %
b101 '
b100011 (
b100011 "
b100011 $
b100011 #
#72000
b110110 !
b110110 %
b110 '
b100100 (
b100100 "
b100100 $
b100100 #
#74000
b110111 !
b110111 %
b111 '
b100101 (
b100101 "
b100101 $
b100101 #
#76000
b111000 !
b111000 %
b1000 '
b100110 (
b100110 "
b100110 $
b100110 #
#78000
b111001 !
b111001 %
b1001 '
b100111 (
b100111 "
b100111 $
b100111 #
#80000
b0 '
b1000000 !
b1000000 %
b100 )
b101000 (
b101000 "
b101000 $
b101000 #
#82000
b1000001 !
b1000001 %
b1 '
b101001 (
b101001 "
b101001 $
b101001 #
#84000
b1000010 !
b1000010 %
b10 '
b101010 (
b101010 "
b101010 $
b101010 #
#86000
b1000011 !
b1000011 %
b11 '
b101011 (
b101011 "
b101011 $
b101011 #
#88000
b1000100 !
b1000100 %
b100 '
b101100 (
b101100 "
b101100 $
b101100 #
#90000
b1000101 !
b1000101 %
b101 '
b101101 (
b101101 "
b101101 $
b101101 #
#92000
b1000110 !
b1000110 %
b110 '
b101110 (
b101110 "
b101110 $
b101110 #
#94000
b1000111 !
b1000111 %
b111 '
b101111 (
b101111 "
b101111 $
b101111 #
#96000
b1001000 !
b1001000 %
b1000 '
b110000 (
b110000 "
b110000 $
b110000 #
#98000
b1001001 !
b1001001 %
b1001 '
b110001 (
b110001 "
b110001 $
b110001 #
#100000
b0 '
b1010000 !
b1010000 %
b101 )
b110010 (
b110010 "
b110010 $
b110010 #
#102000
b1010001 !
b1010001 %
b1 '
b110011 (
b110011 "
b110011 $
b110011 #
#104000
b1010010 !
b1010010 %
b10 '
b110100 (
b110100 "
b110100 $
b110100 #
#106000
b1010011 !
b1010011 %
b11 '
b110101 (
b110101 "
b110101 $
b110101 #
#108000
b1010100 !
b1010100 %
b100 '
b110110 (
b110110 "
b110110 $
b110110 #
#110000
b1010101 !
b1010101 %
b101 '
b110111 (
b110111 "
b110111 $
b110111 #
#112000
b1010110 !
b1010110 %
b110 '
b111000 (
b111000 "
b111000 $
b111000 #
#114000
b1010111 !
b1010111 %
b111 '
b111001 (
b111001 "
b111001 $
b111001 #
#116000
b1011000 !
b1011000 %
b1000 '
b111010 (
b111010 "
b111010 $
b111010 #
#118000
b1011001 !
b1011001 %
b1001 '
b111011 (
b111011 "
b111011 $
b111011 #
#120000
b0 '
b1100000 !
b1100000 %
b110 )
b111100 (
b111100 "
b111100 $
b111100 #
#122000
b1100001 !
b1100001 %
b1 '
b111101 (
b111101 "
b111101 $
b111101 #
#124000
b1100010 !
b1100010 %
b10 '
b111110 (
b111110 "
b111110 $
b111110 #
#126000
b1100011 !
b1100011 %
b11 '
b111111 (
b111111 "
b111111 $
b111111 #
#128000
b1100100 !
b1100100 %
b100 '
b1000000 (
b1000000 "
b1000000 $
b1000000 #
#130000
b1100101 !
b1100101 %
b101 '
b1000001 (
b1000001 "
b1000001 $
b1000001 #
#132000
b1100110 !
b1100110 %
b110 '
b1000010 (
b1000010 "
b1000010 $
b1000010 #
#134000
b1100111 !
b1100111 %
b111 '
b1000011 (
b1000011 "
b1000011 $
b1000011 #
#136000
b1101000 !
b1101000 %
b1000 '
b1000100 (
b1000100 "
b1000100 $
b1000100 #
#138000
b1101001 !
b1101001 %
b1001 '
b1000101 (
b1000101 "
b1000101 $
b1000101 #
#140000
b0 '
b1110000 !
b1110000 %
b111 )
b1000110 (
b1000110 "
b1000110 $
b1000110 #
#142000
b1110001 !
b1110001 %
b1 '
b1000111 (
b1000111 "
b1000111 $
b1000111 #
#144000
b1110010 !
b1110010 %
b10 '
b1001000 (
b1001000 "
b1001000 $
b1001000 #
#146000
b1110011 !
b1110011 %
b11 '
b1001001 (
b1001001 "
b1001001 $
b1001001 #
#148000
b1110100 !
b1110100 %
b100 '
b1001010 (
b1001010 "
b1001010 $
b1001010 #
#150000
b1110101 !
b1110101 %
b101 '
b1001011 (
b1001011 "
b1001011 $
b1001011 #
#152000
b1110110 !
b1110110 %
b110 '
b1001100 (
b1001100 "
b1001100 $
b1001100 #
#154000
b1110111 !
b1110111 %
b111 '
b1001101 (
b1001101 "
b1001101 $
b1001101 #
#156000
b1111000 !
b1111000 %
b1000 '
b1001110 (
b1001110 "
b1001110 $
b1001110 #
#158000
b1111001 !
b1111001 %
b1001 '
b1001111 (
b1001111 "
b1001111 $
b1001111 #
#160000
b0 '
b10000000 !
b10000000 %
b1000 )
b1010000 (
b1010000 "
b1010000 $
b1010000 #
#162000
b10000001 !
b10000001 %
b1 '
b1010001 (
b1010001 "
b1010001 $
b1010001 #
#164000
b10000010 !
b10000010 %
b10 '
b1010010 (
b1010010 "
b1010010 $
b1010010 #
#166000
b10000011 !
b10000011 %
b11 '
b1010011 (
b1010011 "
b1010011 $
b1010011 #
#168000
b10000100 !
b10000100 %
b100 '
b1010100 (
b1010100 "
b1010100 $
b1010100 #
#170000
b10000101 !
b10000101 %
b101 '
b1010101 (
b1010101 "
b1010101 $
b1010101 #
#172000
b10000110 !
b10000110 %
b110 '
b1010110 (
b1010110 "
b1010110 $
b1010110 #
#174000
b10000111 !
b10000111 %
b111 '
b1010111 (
b1010111 "
b1010111 $
b1010111 #
#176000
b10001000 !
b10001000 %
b1000 '
b1011000 (
b1011000 "
b1011000 $
b1011000 #
#178000
b10001001 !
b10001001 %
b1001 '
b1011001 (
b1011001 "
b1011001 $
b1011001 #
#180000
b0 '
b10010000 !
b10010000 %
b1001 )
b1011010 (
b1011010 "
b1011010 $
b1011010 #
#182000
b10010001 !
b10010001 %
b1 '
b1011011 (
b1011011 "
b1011011 $
b1011011 #
#184000
b10010010 !
b10010010 %
b10 '
b1011100 (
b1011100 "
b1011100 $
b1011100 #
#186000
b10010011 !
b10010011 %
b11 '
b1011101 (
b1011101 "
b1011101 $
b1011101 #
#188000
b10010100 !
b10010100 %
b100 '
b1011110 (
b1011110 "
b1011110 $
b1011110 #
#190000
b10010101 !
b10010101 %
b101 '
b1011111 (
b1011111 "
b1011111 $
b1011111 #
#192000
b10010110 !
b10010110 %
b110 '
b1100000 (
b1100000 "
b1100000 $
b1100000 #
#194000
b10010111 !
b10010111 %
b111 '
b1100001 (
b1100001 "
b1100001 $
b1100001 #
#196000
b10011000 !
b10011000 %
b1000 '
b1100010 (
b1100010 "
b1100010 $
b1100010 #
#198000
b10011001 !
b10011001 %
b1001 '
b1100011 (
b1100011 "
b1100011 $
b1100011 #
#200000
b0 '
b0 )
b0 (
b100000000 !
b100000000 %
b1 &
b1100100 "
b1100100 $
b1100100 #
#202000
b100000001 !
b100000001 %
b1 '
b1 (
b1100101 "
b1100101 $
b1100101 #
#204000
b100000010 !
b100000010 %
b10 '
b10 (
b1100110 "
b1100110 $
b1100110 #
#206000
b100000011 !
b100000011 %
b11 '
b11 (
b1100111 "
b1100111 $
b1100111 #
#208000
b100000100 !
b100000100 %
b100 '
b100 (
b1101000 "
b1101000 $
b1101000 #
#210000
b100000101 !
b100000101 %
b101 '
b101 (
b1101001 "
b1101001 $
b1101001 #
#212000
b100000110 !
b100000110 %
b110 '
b110 (
b1101010 "
b1101010 $
b1101010 #
#214000
b100000111 !
b100000111 %
b111 '
b111 (
b1101011 "
b1101011 $
b1101011 #
#216000
b100001000 !
b100001000 %
b1000 '
b1000 (
b1101100 "
b1101100 $
b1101100 #
#218000
b100001001 !
b100001001 %
b1001 '
b1001 (
b1101101 "
b1101101 $
b1101101 #
#220000
b0 '
b100010000 !
b100010000 %
b1 )
b1010 (
b1101110 "
b1101110 $
b1101110 #
#222000
b100010001 !
b100010001 %
b1 '
b1011 (
b1101111 "
b1101111 $
b1101111 #
#224000
b100010010 !
b100010010 %
b10 '
b1100 (
b1110000 "
b1110000 $
b1110000 #
#226000
b100010011 !
b100010011 %
b11 '
b1101 (
b1110001 "
b1110001 $
b1110001 #
#228000
b100010100 !
b100010100 %
b100 '
b1110 (
b1110010 "
b1110010 $
b1110010 #
#230000
b100010101 !
b100010101 %
b101 '
b1111 (
b1110011 "
b1110011 $
b1110011 #
#232000
b100010110 !
b100010110 %
b110 '
b10000 (
b1110100 "
b1110100 $
b1110100 #
#234000
b100010111 !
b100010111 %
b111 '
b10001 (
b1110101 "
b1110101 $
b1110101 #
#236000
b100011000 !
b100011000 %
b1000 '
b10010 (
b1110110 "
b1110110 $
b1110110 #
#238000
b100011001 !
b100011001 %
b1001 '
b10011 (
b1110111 "
b1110111 $
b1110111 #
#240000
b0 '
b100100000 !
b100100000 %
b10 )
b10100 (
b1111000 "
b1111000 $
b1111000 #
#242000
b100100001 !
b100100001 %
b1 '
b10101 (
b1111001 "
b1111001 $
b1111001 #
#244000
b100100010 !
b100100010 %
b10 '
b10110 (
b1111010 "
b1111010 $
b1111010 #
#246000
b100100011 !
b100100011 %
b11 '
b10111 (
b1111011 "
b1111011 $
b1111011 #
#248000
b100100100 !
b100100100 %
b100 '
b11000 (
b1111100 "
b1111100 $
b1111100 #
#250000
b100100101 !
b100100101 %
b101 '
b11001 (
b1111101 "
b1111101 $
b1111101 #
#252000
b100100110 !
b100100110 %
b110 '
b11010 (
b1111110 "
b1111110 $
b1111110 #
#254000
b100100111 !
b100100111 %
b111 '
b11011 (
b1111111 "
b1111111 $
b1111111 #
#256000
b100101000 !
b100101000 %
b1000 '
b11100 (
b10000000 "
b10000000 $
b10000000 #
#258000
b100101001 !
b100101001 %
b1001 '
b11101 (
b10000001 "
b10000001 $
b10000001 #
#260000
b0 '
b100110000 !
b100110000 %
b11 )
b11110 (
b10000010 "
b10000010 $
b10000010 #
#262000
b100110001 !
b100110001 %
b1 '
b11111 (
b10000011 "
b10000011 $
b10000011 #
#264000
b100110010 !
b100110010 %
b10 '
b100000 (
b10000100 "
b10000100 $
b10000100 #
#266000
b100110011 !
b100110011 %
b11 '
b100001 (
b10000101 "
b10000101 $
b10000101 #
#268000
b100110100 !
b100110100 %
b100 '
b100010 (
b10000110 "
b10000110 $
b10000110 #
#270000
b100110101 !
b100110101 %
b101 '
b100011 (
b10000111 "
b10000111 $
b10000111 #
#272000
b100110110 !
b100110110 %
b110 '
b100100 (
b10001000 "
b10001000 $
b10001000 #
#274000
b100110111 !
b100110111 %
b111 '
b100101 (
b10001001 "
b10001001 $
b10001001 #
#276000
b100111000 !
b100111000 %
b1000 '
b100110 (
b10001010 "
b10001010 $
b10001010 #
#278000
b100111001 !
b100111001 %
b1001 '
b100111 (
b10001011 "
b10001011 $
b10001011 #
#280000
b0 '
b101000000 !
b101000000 %
b100 )
b101000 (
b10001100 "
b10001100 $
b10001100 #
#282000
b101000001 !
b101000001 %
b1 '
b101001 (
b10001101 "
b10001101 $
b10001101 #
#284000
b101000010 !
b101000010 %
b10 '
b101010 (
b10001110 "
b10001110 $
b10001110 #
#286000
b101000011 !
b101000011 %
b11 '
b101011 (
b10001111 "
b10001111 $
b10001111 #
#288000
b101000100 !
b101000100 %
b100 '
b101100 (
b10010000 "
b10010000 $
b10010000 #
#290000
b101000101 !
b101000101 %
b101 '
b101101 (
b10010001 "
b10010001 $
b10010001 #
#292000
b101000110 !
b101000110 %
b110 '
b101110 (
b10010010 "
b10010010 $
b10010010 #
#294000
b101000111 !
b101000111 %
b111 '
b101111 (
b10010011 "
b10010011 $
b10010011 #
#296000
b101001000 !
b101001000 %
b1000 '
b110000 (
b10010100 "
b10010100 $
b10010100 #
#298000
b101001001 !
b101001001 %
b1001 '
b110001 (
b10010101 "
b10010101 $
b10010101 #
#300000
b0 '
b101010000 !
b101010000 %
b101 )
b110010 (
b10010110 "
b10010110 $
b10010110 #
#302000
b101010001 !
b101010001 %
b1 '
b110011 (
b10010111 "
b10010111 $
b10010111 #
#304000
b101010010 !
b101010010 %
b10 '
b110100 (
b10011000 "
b10011000 $
b10011000 #
#306000
b101010011 !
b101010011 %
b11 '
b110101 (
b10011001 "
b10011001 $
b10011001 #
#308000
b101010100 !
b101010100 %
b100 '
b110110 (
b10011010 "
b10011010 $
b10011010 #
#310000
b101010101 !
b101010101 %
b101 '
b110111 (
b10011011 "
b10011011 $
b10011011 #
#312000
b101010110 !
b101010110 %
b110 '
b111000 (
b10011100 "
b10011100 $
b10011100 #
#314000
b101010111 !
b101010111 %
b111 '
b111001 (
b10011101 "
b10011101 $
b10011101 #
#316000
b101011000 !
b101011000 %
b1000 '
b111010 (
b10011110 "
b10011110 $
b10011110 #
#318000
b101011001 !
b101011001 %
b1001 '
b111011 (
b10011111 "
b10011111 $
b10011111 #
#320000
b0 '
b101100000 !
b101100000 %
b110 )
b111100 (
b10100000 "
b10100000 $
b10100000 #
#322000
b101100001 !
b101100001 %
b1 '
b111101 (
b10100001 "
b10100001 $
b10100001 #
#324000
b101100010 !
b101100010 %
b10 '
b111110 (
b10100010 "
b10100010 $
b10100010 #
#326000
b101100011 !
b101100011 %
b11 '
b111111 (
b10100011 "
b10100011 $
b10100011 #
#328000
b101100100 !
b101100100 %
b100 '
b1000000 (
b10100100 "
b10100100 $
b10100100 #
#330000
b101100101 !
b101100101 %
b101 '
b1000001 (
b10100101 "
b10100101 $
b10100101 #
#332000
b101100110 !
b101100110 %
b110 '
b1000010 (
b10100110 "
b10100110 $
b10100110 #
#334000
b101100111 !
b101100111 %
b111 '
b1000011 (
b10100111 "
b10100111 $
b10100111 #
#336000
b101101000 !
b101101000 %
b1000 '
b1000100 (
b10101000 "
b10101000 $
b10101000 #
#338000
b101101001 !
b101101001 %
b1001 '
b1000101 (
b10101001 "
b10101001 $
b10101001 #
#340000
b0 '
b101110000 !
b101110000 %
b111 )
b1000110 (
b10101010 "
b10101010 $
b10101010 #
#342000
b101110001 !
b101110001 %
b1 '
b1000111 (
b10101011 "
b10101011 $
b10101011 #
#344000
b101110010 !
b101110010 %
b10 '
b1001000 (
b10101100 "
b10101100 $
b10101100 #
#346000
b101110011 !
b101110011 %
b11 '
b1001001 (
b10101101 "
b10101101 $
b10101101 #
#348000
b101110100 !
b101110100 %
b100 '
b1001010 (
b10101110 "
b10101110 $
b10101110 #
#350000
b101110101 !
b101110101 %
b101 '
b1001011 (
b10101111 "
b10101111 $
b10101111 #
#352000
b101110110 !
b101110110 %
b110 '
b1001100 (
b10110000 "
b10110000 $
b10110000 #
#354000
b101110111 !
b101110111 %
b111 '
b1001101 (
b10110001 "
b10110001 $
b10110001 #
#356000
b101111000 !
b101111000 %
b1000 '
b1001110 (
b10110010 "
b10110010 $
b10110010 #
#358000
b101111001 !
b101111001 %
b1001 '
b1001111 (
b10110011 "
b10110011 $
b10110011 #
#360000
b0 '
b110000000 !
b110000000 %
b1000 )
b1010000 (
b10110100 "
b10110100 $
b10110100 #
#362000
b110000001 !
b110000001 %
b1 '
b1010001 (
b10110101 "
b10110101 $
b10110101 #
#364000
b110000010 !
b110000010 %
b10 '
b1010010 (
b10110110 "
b10110110 $
b10110110 #
#366000
b110000011 !
b110000011 %
b11 '
b1010011 (
b10110111 "
b10110111 $
b10110111 #
#368000
b110000100 !
b110000100 %
b100 '
b1010100 (
b10111000 "
b10111000 $
b10111000 #
#370000
b110000101 !
b110000101 %
b101 '
b1010101 (
b10111001 "
b10111001 $
b10111001 #
#372000
b110000110 !
b110000110 %
b110 '
b1010110 (
b10111010 "
b10111010 $
b10111010 #
#374000
b110000111 !
b110000111 %
b111 '
b1010111 (
b10111011 "
b10111011 $
b10111011 #
#376000
b110001000 !
b110001000 %
b1000 '
b1011000 (
b10111100 "
b10111100 $
b10111100 #
#378000
b110001001 !
b110001001 %
b1001 '
b1011001 (
b10111101 "
b10111101 $
b10111101 #
#380000
b0 '
b110010000 !
b110010000 %
b1001 )
b1011010 (
b10111110 "
b10111110 $
b10111110 #
#382000
b110010001 !
b110010001 %
b1 '
b1011011 (
b10111111 "
b10111111 $
b10111111 #
#384000
b110010010 !
b110010010 %
b10 '
b1011100 (
b11000000 "
b11000000 $
b11000000 #
#386000
b110010011 !
b110010011 %
b11 '
b1011101 (
b11000001 "
b11000001 $
b11000001 #
#388000
b110010100 !
b110010100 %
b100 '
b1011110 (
b11000010 "
b11000010 $
b11000010 #
#390000
b110010101 !
b110010101 %
b101 '
b1011111 (
b11000011 "
b11000011 $
b11000011 #
#392000
b110010110 !
b110010110 %
b110 '
b1100000 (
b11000100 "
b11000100 $
b11000100 #
#394000
b110010111 !
b110010111 %
b111 '
b1100001 (
b11000101 "
b11000101 $
b11000101 #
#396000
b110011000 !
b110011000 %
b1000 '
b1100010 (
b11000110 "
b11000110 $
b11000110 #
#398000
b110011001 !
b110011001 %
b1001 '
b1100011 (
b11000111 "
b11000111 $
b11000111 #
#400000
b0 '
b0 )
b0 (
b1000000000 !
b1000000000 %
b10 &
b11001000 "
b11001000 $
b11001000 #
#402000
b1000000001 !
b1000000001 %
b1 '
b1 (
b11001001 "
b11001001 $
b11001001 #
#404000
b1000000010 !
b1000000010 %
b10 '
b10 (
b11001010 "
b11001010 $
b11001010 #
#406000
b1000000011 !
b1000000011 %
b11 '
b11 (
b11001011 "
b11001011 $
b11001011 #
#408000
b1000000100 !
b1000000100 %
b100 '
b100 (
b11001100 "
b11001100 $
b11001100 #
#410000
b1000000101 !
b1000000101 %
b101 '
b101 (
b11001101 "
b11001101 $
b11001101 #
#412000
b1000000110 !
b1000000110 %
b110 '
b110 (
b11001110 "
b11001110 $
b11001110 #
#414000
b1000000111 !
b1000000111 %
b111 '
b111 (
b11001111 "
b11001111 $
b11001111 #
#416000
b1000001000 !
b1000001000 %
b1000 '
b1000 (
b11010000 "
b11010000 $
b11010000 #
#418000
b1000001001 !
b1000001001 %
b1001 '
b1001 (
b11010001 "
b11010001 $
b11010001 #
#420000
b0 '
b1000010000 !
b1000010000 %
b1 )
b1010 (
b11010010 "
b11010010 $
b11010010 #
#422000
b1000010001 !
b1000010001 %
b1 '
b1011 (
b11010011 "
b11010011 $
b11010011 #
#424000
b1000010010 !
b1000010010 %
b10 '
b1100 (
b11010100 "
b11010100 $
b11010100 #
#426000
b1000010011 !
b1000010011 %
b11 '
b1101 (
b11010101 "
b11010101 $
b11010101 #
#428000
b1000010100 !
b1000010100 %
b100 '
b1110 (
b11010110 "
b11010110 $
b11010110 #
#430000
b1000010101 !
b1000010101 %
b101 '
b1111 (
b11010111 "
b11010111 $
b11010111 #
#432000
b1000010110 !
b1000010110 %
b110 '
b10000 (
b11011000 "
b11011000 $
b11011000 #
#434000
b1000010111 !
b1000010111 %
b111 '
b10001 (
b11011001 "
b11011001 $
b11011001 #
#436000
b1000011000 !
b1000011000 %
b1000 '
b10010 (
b11011010 "
b11011010 $
b11011010 #
#438000
b1000011001 !
b1000011001 %
b1001 '
b10011 (
b11011011 "
b11011011 $
b11011011 #
#440000
b0 '
b1000100000 !
b1000100000 %
b10 )
b10100 (
b11011100 "
b11011100 $
b11011100 #
#442000
b1000100001 !
b1000100001 %
b1 '
b10101 (
b11011101 "
b11011101 $
b11011101 #
#444000
b1000100010 !
b1000100010 %
b10 '
b10110 (
b11011110 "
b11011110 $
b11011110 #
#446000
b1000100011 !
b1000100011 %
b11 '
b10111 (
b11011111 "
b11011111 $
b11011111 #
#448000
b1000100100 !
b1000100100 %
b100 '
b11000 (
b11100000 "
b11100000 $
b11100000 #
#450000
b1000100101 !
b1000100101 %
b101 '
b11001 (
b11100001 "
b11100001 $
b11100001 #
#452000
b1000100110 !
b1000100110 %
b110 '
b11010 (
b11100010 "
b11100010 $
b11100010 #
#454000
b1000100111 !
b1000100111 %
b111 '
b11011 (
b11100011 "
b11100011 $
b11100011 #
#456000
b1000101000 !
b1000101000 %
b1000 '
b11100 (
b11100100 "
b11100100 $
b11100100 #
#458000
b1000101001 !
b1000101001 %
b1001 '
b11101 (
b11100101 "
b11100101 $
b11100101 #
#460000
b0 '
b1000110000 !
b1000110000 %
b11 )
b11110 (
b11100110 "
b11100110 $
b11100110 #
#462000
b1000110001 !
b1000110001 %
b1 '
b11111 (
b11100111 "
b11100111 $
b11100111 #
#464000
b1000110010 !
b1000110010 %
b10 '
b100000 (
b11101000 "
b11101000 $
b11101000 #
#466000
b1000110011 !
b1000110011 %
b11 '
b100001 (
b11101001 "
b11101001 $
b11101001 #
#468000
b1000110100 !
b1000110100 %
b100 '
b100010 (
b11101010 "
b11101010 $
b11101010 #
#470000
b1000110101 !
b1000110101 %
b101 '
b100011 (
b11101011 "
b11101011 $
b11101011 #
#472000
b1000110110 !
b1000110110 %
b110 '
b100100 (
b11101100 "
b11101100 $
b11101100 #
#474000
b1000110111 !
b1000110111 %
b111 '
b100101 (
b11101101 "
b11101101 $
b11101101 #
#476000
b1000111000 !
b1000111000 %
b1000 '
b100110 (
b11101110 "
b11101110 $
b11101110 #
#478000
b1000111001 !
b1000111001 %
b1001 '
b100111 (
b11101111 "
b11101111 $
b11101111 #
#480000
b0 '
b1001000000 !
b1001000000 %
b100 )
b101000 (
b11110000 "
b11110000 $
b11110000 #
#482000
b1001000001 !
b1001000001 %
b1 '
b101001 (
b11110001 "
b11110001 $
b11110001 #
#484000
b1001000010 !
b1001000010 %
b10 '
b101010 (
b11110010 "
b11110010 $
b11110010 #
#486000
b1001000011 !
b1001000011 %
b11 '
b101011 (
b11110011 "
b11110011 $
b11110011 #
#488000
b1001000100 !
b1001000100 %
b100 '
b101100 (
b11110100 "
b11110100 $
b11110100 #
#490000
b1001000101 !
b1001000101 %
b101 '
b101101 (
b11110101 "
b11110101 $
b11110101 #
#492000
b1001000110 !
b1001000110 %
b110 '
b101110 (
b11110110 "
b11110110 $
b11110110 #
#494000
b1001000111 !
b1001000111 %
b111 '
b101111 (
b11110111 "
b11110111 $
b11110111 #
#496000
b1001001000 !
b1001001000 %
b1000 '
b110000 (
b11111000 "
b11111000 $
b11111000 #
#498000
b1001001001 !
b1001001001 %
b1001 '
b110001 (
b11111001 "
b11111001 $
b11111001 #
#500000
b0 '
b1001010000 !
b1001010000 %
b101 )
b110010 (
b11111010 "
b11111010 $
b11111010 #
#502000
b1001010001 !
b1001010001 %
b1 '
b110011 (
b11111011 "
b11111011 $
b11111011 #
#504000
b1001010010 !
b1001010010 %
b10 '
b110100 (
b11111100 "
b11111100 $
b11111100 #
#506000
b1001010011 !
b1001010011 %
b11 '
b110101 (
b11111101 "
b11111101 $
b11111101 #
#508000
b1001010100 !
b1001010100 %
b100 '
b110110 (
b11111110 "
b11111110 $
b11111110 #
#510000
b1001010101 !
b1001010101 %
b101 '
b110111 (
b11111111 "
b11111111 $
b11111111 #
#512000
b100000000 #
