Code Converters/Binary to BCD/bin2bcd.v
`timescale 1ns / 1ps
//////////////////////////////////////////////////////////////////////////////////
// 
// Create Date: 02/15/2025 07:54:58 PM
// Creator Name: Sk Mahamamd Anish
// Module Name: bin2bcd
// Project Name: Code Converter
// 
// Dependencies: 
// 
// Revision 0.01 - File Created
// 
//////////////////////////////////////////////////////////////////////////////////

module bin2bcd(
	input  [7:0] bin_in,
	output [7:0] bcd_out
);

	reg [3:0] tens, ones;

	always @(*) begin
		tens = bin_in / 10;
		ones = bin_in % 10;
	end

	assign bcd_out = {tens, ones};

endmodule

Code Converters/Binary to BCD/bin2bcd_TB.v
`timescale 1ns / 1ps
//////////////////////////////////////////////////////////////////////////////////
// 
// Create Date: 02/15/2025 07:54:58 PM
// Creator Name: Sk Mahamamd Anish
// Module Name: bin2bcd_TB
// Project Name: Code Converter
// 
// Dependencies: 
// 
// Revision 0.01 - File Created
// 
//////////////////////////////////////////////////////////////////////////////////

module bin2bcd_TB;

	reg  [7:0] bin_in;
	wire [7:0] bcd_out;

	bin2bcd DUT(.bin_in(bin_in), .bcd_out(bcd_out));

	integer i;
	
	initial begin
		for(i = 0; i < 60; i = i + 1) begin
			bin_in = i;
			#2;
		end
	end

	initial begin
		$monitor("%t	|	bin_in = %b --> bcd_out = %b ", $time, bin_in, bcd_out);
		$dumpfile("bin2bcd_TB.vcd") ;
		$dumpvars(0, bin2bcd_TB) ;
    end

endmodule

Code Converters/Binary to BCD/bin2bcd_TB.vcd
$date
	Mon Feb 17 21:36:56 2025
$end
$version
	Icarus Verilog
$end
$timescale
	1ps
$end
$scope module bin2bcd_TB $end
$var wire 8 ! bcd_out [7:0] $end
$var reg 8 " bin_in [7:0] $end
$var integer 32 # i [31:0] $end
$scope module DUT $end
$var wire 8 $ bin_in [7:0] $end
$var wire 8 % bcd_out [7:0] $end
$var reg 4 & ones [3:0] $end
$var reg 4 ' tens [3:0] $end
$upscope $end
$upscope $end
$enddefinitions $end
$comment Show the parameter values. $end
$dumpall
$end
#0
$dumpvars
b0 '
b0 &
b0 %
b0 $
b0 #
b0 "
b0 !
$end
#2000
b1 !
b1 %
b1 &
b1 "
b1 $
b1 #
#4000
b10 !
b10 %
b10 &
b10 "
b10 $
b10 #
#6000
b11 !
b11 %
b11 &
b11 "
b11 $
b11 #
#8000
b100 !
b100 %
b100 &
b100 "
b100 $
b100 #
#10000
b101 !
b101 %
b101 &
b101 "
b101 $
b101 #
#12000
b110 !
b110 %
b110 &
b110 "
b110 $
b110 #
#14000
b111 !
b111 %
b111 &
b111 "
b111 $
b111 #
#16000
b1000 !
b1000 %
b1000 &
b1000 "
b1000 $
b1000 #
#18000
b1001 !
b1001 %
b1001 &
b1001 "
b1001 $
b1001 #
#20000
b0 &
b10000 !
b10000 %
b1 '
b1010 "
b1010 $
b1010 #
#22000
b10001 !
b10001 %
b1 &
b1011 "
b1011 $
b1011 #
#24000
b10010 !
b10010 %
b10 &
b1100 "
b1100 $
b1100 #
#26000
b10011 !
b10011 %
b11 &
b1101 "
b1101 $
b1101 #
#28000
b10100 !
b10100 %
b100 &
b1110 "
b1110 $
b1110 #
#30000
b10101 !
b10101 %
b101 &
b1111 "
b1111 $
b1111 #
#32000
b10110 !
b10110 %
b110 &
b10000 "
b10000 $
b10000 #
#34000
b10111 !
b10111 %
b111 &
b10001 "
b10001 $
b10001 #
#36000
b11000 !
b11000 %
b1000 &
b10010 "
b10010 $
b10010 #
#38000
b11001 !
b11001 %
b1001 &
b10011 "
b10011 $
b10011 #
#40000
b0 &
b100000 !
b100000 %
b10 '
b10100 "
b10100 $
b10100 #
#42000
b100001 !
b100001 %
b1 &
b10101 "
b10101 $
b10101 #
#44000
b100010 !
b100010 %
b10 &
b10110 "
b10110 $
b10110 #
#46000
b100011 !
b100011 %
b11 &
b10111 "
b10111 $
b10111 #
#48000
b100100 !
b100100 %
b100 &
b11000 "
b11000 $
b11000 #
#50000
b100101 !
b100101 %
b101 &
b11001 "
b11001 $
b11001 #
#52000
b100110 !
b100110 %
b110 &
b11010 "
b11010 $
b11010 #
#54000
b100111 !
b100111 %
b111 &
b11011 "
b11011 $
b11011 #
#56000
b101000 !
b101000 %
b1000 &
b11100 "
b11100 $
b11100 #
#58000
b101001 !
b101001 %
b1001 &
b11101 "
b11101 $
b11101 #
#60000
b0 &
b110000 !
b110000 %
b11 '
b11110 "
b11110 $
b11110 #
#62000
b110001 !
b110001 %
b1 &
b11111 "
b11111 $
b11111 #
#64000
b110010 !
b110010 %
b10 &
b100000 "
b100000 $
b100000 #
#66000
b110011 !
b110011 %
b11 &
b100001 "
b100001 $
b100001 #
#68000
b110100 !
b110100 %
b100 &
b100010 "
b100010 $
b100010 #
#70000
b110101 !
b110101 %
b101 &
b100011 "
b100011 $
b100011 #
#72000
b110110 !
b110110 %
b110 &
b100100 "
b100100 $
b100100 #
#74000
b110111 !
b110111 %
b111 &
b100101 "
b100101 $
b100101 #
#76000
b111000 !
b111000 %
b1000 &
b100110 "
b100110 $
b100110 #
#78000
b111001 !
b111001 %
b1001 &
b100111 "
b100111 $
b100111 #
#80000
b0 &
b1000000 !
b1000000 %
b100 '
b101000 "
b101000 $
b101000 #
#82000
b1000001 !
b1000001 %
b1 &
b101001 "
b101001 $
b101001 #
#84000
b1000010 !
b1000010 %
b10 &
b101010 "
b101010 $
b101010 #
#86000
b1000011 !
b1000011 %
b11 &
b101011 "
b101011 $
b101011 #
#88000
b1000100 !
b1000100 %
b100 &
b101100 "
b101100 $
b101100 #
#90000
b1000101 !
b1000101 %
b101 &
b101101 "
b101101 $
b101101 #
#92000
b1000110 !
b1000110 %
b110 &
b101110 "
b101110 $
b101110 #
#94000
b1000111 !
b1000111 %
b111 &
b101111 "
b101111 $
b101111 #
#96000
b1001000 !
b1001000 %
b1000 &
b110000 "
b110000 $
b110000 #
#98000
b1001001 !
b1001001 %
b1001 &
b110001 "
b110001 $
b110001 #
#100000
b0 &
b1010000 !
b1010000 %
b101 '
b110010 "
b110010 $
b110010 #
#102000
b1010001 !
b1010001 %
b1 &
b110011 "
b110011 $
b110011 #
#104000
b1010010 !
b1010010 %
b10 &
b110100 "
b110100 $
b110100 #
#106000
b1010011 !
b1010011 %
b11 &
b110101 "
b110101 $
b110101 #
#108000
b1010100 !
b1010100 %
b100 &
b110110 "
b110110 $
b110110 #
#110000
b1010101 !
b1010101 %
b101 &
b110111 "
b110111 $
b110111 #
#112000
b1010110 !
b1010110 %
b110 &
b111000 "
b111000 $
b111000 #
#114000
b1010111 !
b1010111 %
b111 &
b111001 "
b111001 $
b111001 #
#116000
b1011000 !
b1011000 %
b1000 &
b111010 "
b111010 $
b111010 #
#118000
b1011001 !
b1011001 %
b1001 &
b111011 "
b111011 $
b111011 #
#120000
b111100 #
